[{"_id":"5900f255c46b2b06542f5f64","slug":"networking","name":"Improv + Networking","color":"blue","price":750,"__v":0,"packages":[],"materials":["58d3e622b385ee0238d3d8b4","58d3e622b385ee0238d3d8be","58d3e622b385ee0238d3d8bc","58d3e622b385ee0238d3d8b2"],"dateModified":"2017-04-26T19:17:41.551Z","dateAdded":"2017-04-26T19:19:53.010Z","description":["Train your participants to present themselves with confidence."]},{"_id":"5900f255c46b2b06542f5f65","slug":"leadership","name":"Improv + Leadership","color":"orange","price":1500,"__v":0,"packages":[],"materials":["58d3e622b385ee0238d3d8b8","58d3e622b385ee0238d3d8b6","58d3e622b385ee0238d3d8b2","58d3e622b385ee0238d3d8ba"],"dateModified":"2017-04-26T19:17:41.558Z","dateAdded":"2017-04-26T19:19:53.010Z","description":["Help your participants be better Collaborators, Speakers, Creators, and Problem-Solvers."]},{"_id":"58d814593d8da4419cdbc0f1","slug":"ultimate","name":"Improv + Ultimate","color":"red","price":2000,"__v":0,"packages":["5900f255c46b2b06542f5f64","5900f255c46b2b06542f5f65"],"materials":[],"dateModified":"2017-04-26T19:17:41.558Z","dateAdded":"2017-03-26T19:19:53.010Z","description":["Own all of the ImprovPlus materials currently available.","Access our unbeatable hands-on support and coaching."]}]